bfibundle/__init__.py
bfibundle/src/__init__.py
bfibundle/src/bfibundle.py
bfibundle/src/models.py
bfibundle/src/utils.py
bfibundle/test/__init__.py
bfibundle/test/test_bfibundle.py
bfibundle-0.1.0.dist-info/LICENSE
bfibundle-0.1.0.dist-info/METADATA
bfibundle-0.1.0.dist-info/WHEEL
bfibundle-0.1.0.dist-info/top_level.txt
bfibundle-0.1.0.dist-info/RECORD
