Metadata-Version: 2.1
Name: bfibundle
Version: 0.1.0
Summary: A python package to explore categorized bfi data
Home-page: https://github.com/Michal-Babins/BFIBundle
Author: Michal Babinski
Author-email: mbabinski@lanl.gov
License: MIT
Classifier: License :: OSI Approved :: MIT License
Classifier: Programming Language :: Python :: 3.9
Classifier: Operating System :: OS Independent
Requires-Python: >=3.9
License-File: LICENSE
Requires-Dist: crossrefapi (>=1.5.0)
Requires-Dist: pydantic (>=1.10.6)
Provides-Extra: dev
Requires-Dist: pytest (>=7.0) ; extra == 'dev'
Requires-Dist: twine (>=4.0.2) ; extra == 'dev'
